the_conf/__init__.py
the_conf/__main__.py
the_conf/command_line.py
the_conf/environement.py
the_conf/files.py
the_conf/interractive.py
the_conf/node.py
the_conf/the_conf.py
the_conf/utils.py
the_conf-1.0.8.dist-info/LICENSE
the_conf-1.0.8.dist-info/METADATA
the_conf-1.0.8.dist-info/WHEEL
the_conf-1.0.8.dist-info/entry_points.txt
the_conf-1.0.8.dist-info/RECORD
