Metadata-Version: 2.3
Name: the_conf
Version: 1.0.8
Summary: Config build from multiple sources
License: GPLv3
Keywords: conf,configuration,json,yaml
Author: François Schmidts
Author-email: francois@schmidts.fr
Requires-Python: >=3.9
Classifier: License :: OSI Approved :: GNU General Public License v3 (GPLv3)
Classifier: License :: Other/Proprietary License
Classifier: Programming Language :: Python :: 3
Classifier: Programming Language :: Python :: 3.9
Classifier: Programming Language :: Python :: 3.10
Classifier: Programming Language :: Python :: 3.11
Classifier: Programming Language :: Python :: 3.12
Classifier: Programming Language :: Python :: 3.13
Requires-Dist: pycryptodome (>=3.21.0,<4.0.0)
Requires-Dist: pyyaml
Project-URL: Documentation, https://github.com/jaesivsm/the_conf#readme
Project-URL: Homepage, https://github.com/jaesivsm/the_conf
Project-URL: Repository, https://github.com/jaesivsm/the_conf
